{
  "name": "Aaron Howard",
  "title": "Full Stack Developer",
  "location": "Irving, USA",
  "about": "I'm a passionate full-stack developer with a love for creating elegant, user-friendly applications. With several years of experience in web development, I specialize in modern JavaScript frameworks, cloud technologies, and building scalable solutions that solve real-world problems.",
  "skills": {
    "frontend": ["React", "Vue.js", "Svelte", "TypeScript", "Tailwind CSS", "Next.js"],
    "backend": ["Node.js", "Python", "PostgreSQL", "MongoDB", "Express.js", "FastAPI"],
    "tools": ["Git", "Docker", "Netlify", "Vercel", "Figma", "Postman"],
    "languages": ["JavaScript", "TypeScript", "Python", "SQL", "HTML/CSS"]
  },
  "experience": [
    {
      "title": "Senior Full Stack Developer",
      "company": "City of Dallas",
      "period": "2022 - Present",
      "description": "Leading development of web applications using React, Node.js, and cloud technologies. Certified Advanced Scrum Master for our ServiceNow Platform."
    },
    {
      "title": "Frontend Developer",
      "company": "City of Dallas",
      "period": "2020 - 2022",
      "description": "Built responsive user interfaces and improved user experience across multiple products."
    },
    {
      "title": "Junior Developer",
      "company": "City of Dallas",
      "period": "2015 - 2020",
      "description": "Developed websites and web applications for various clients using modern technologies."
    }
  ],
  "education": [
    {
      "degree": "Bachelor of Business Administration in Business Analytics",
      "school": "East Texas A&M University",
      "period": "2015 - 2019",
      "description": "Focused on software engineering and web development"
    },
    {
      "degree": "Associate of Applied Science in Computer Science",
      "school": "Front Range Community College",
      "period": "2013 - 2015",
      "description": "Focused on software engineering and web development"
    }
  ],
  "interests": [
    "Open Source Development",
    "Machine Learning",
    "UI/UX Design",
    "Cloud Architecture",
    "Technical Writing"
  ]
}


